pytesseract_api/__init__.py
pytesseract_api/api.py
pytesseract_api/capi_types.py
pytesseract_api/exceptions.py
pytesseract_api/py.typed
pytesseract_api-1.0.4.dist-info/LICENSE
pytesseract_api-1.0.4.dist-info/METADATA
pytesseract_api-1.0.4.dist-info/WHEEL
pytesseract_api-1.0.4.dist-info/top_level.txt
pytesseract_api-1.0.4.dist-info/RECORD
