Metadata-Version: 2.1
Name: pytesseract-api
Version: 1.0.4
Summary: Tesseract C-API in python, a faster alternative to pytesseract
Home-page: https://github.com/sandbox-pokhara/pytesseract-api
Author: Pradish Bijukchhe
Author-email: pradishbijukchhe@gmail.com
Project-URL: Bug Tracker, https://github.com/sandbox-pokhara/pytesseract-api/issues
Classifier: Programming Language :: Python :: 3
Classifier: License :: OSI Approved :: MIT License
Requires-Python: >=3
License-File: LICENSE
